astri_eda/.DS_Store
astri_eda/__init__.py
astri_eda/layout_generator/__init__.py
astri_eda/netlist_loader/__init__.py
astri_eda/netlist_loader/read_spice.py
astri_eda/pdk_loader/__init__.py
astri_eda/pr_engine/__init__.py
astri_eda/schema/.DS_Store
astri_eda/schema/__init__.py
astri_eda/schema/checker.py
astri_eda/schema/constraint.py
astri_eda/schema/gen_dot.py
astri_eda/schema/graph.py
astri_eda/schema/hacks.py
astri_eda/schema/instance.py
astri_eda/schema/library.py
astri_eda/schema/model.py
astri_eda/schema/parser.py
astri_eda/schema/pdk.py
astri_eda/schema/subcircuit.py
astri_eda/schema/transistor.py
astri_eda/schema/translator.py
astri_eda/schema/types.py
astri_eda/schema/visitor.py
astri_eda/utils/__init__.py
astri_eda/utils/fileio.py
astri_eda/utils/logging.py
astri_eda-0.1.2.dist-info/METADATA
astri_eda-0.1.2.dist-info/WHEEL
astri_eda-0.1.2.dist-info/RECORD
